sourcefinder/__init__.py
sourcefinder/_version.py
sourcefinder/config.py
sourcefinder/deconv.py
sourcefinder/extract.py
sourcefinder/gaussian.py
sourcefinder/image.py
sourcefinder/measuring.py
sourcefinder/stats.py
sourcefinder/utils.py
sourcefinder/accessors/__init__.py
sourcefinder/accessors/aartfaaccasaimage.py
sourcefinder/accessors/amicasaimage.py
sourcefinder/accessors/casaimage.py
sourcefinder/accessors/dataaccessor.py
sourcefinder/accessors/detection.py
sourcefinder/accessors/fitsimage.py
sourcefinder/accessors/fitsimageblob.py
sourcefinder/accessors/kat7casaimage.py
sourcefinder/accessors/lofaraccessor.py
sourcefinder/accessors/lofarcasaimage.py
sourcefinder/accessors/lofarfitsimage.py
sourcefinder/accessors/lofarhdf5image.py
sourcefinder/testutil/__init__.py
sourcefinder/testutil/convolve.py
sourcefinder/testutil/decorators.py
sourcefinder/testutil/mock.py
sourcefinder/utility/__init__.py
sourcefinder/utility/cli.py
sourcefinder/utility/containers.py
sourcefinder/utility/coordinates.py
sourcefinder/utility/sourceparams.py
sourcefinder/utility/uncertain.py
radio_pyse-0.6.0.dist-info/METADATA
radio_pyse-0.6.0.dist-info/WHEEL
radio_pyse-0.6.0.dist-info/entry_points.txt
radio_pyse-0.6.0.dist-info/licenses/LICENSE
radio_pyse-0.6.0.dist-info/RECORD
