Metadata-Version: 2.4
Name: radio-pyse
Version: 0.6.0
Summary: Python Source Extractor
Project-URL: Homepage, http://docs.transientskp.org/
Author-email: TKP Discovery WG <discovery@transientskp.org>
License: BSD 2-Clause License
License-File: LICENSE
Requires-Python: <3.14,>=3.10
Requires-Dist: astropy
Requires-Dist: enum-tools[sphinx]
Requires-Dist: numba
Requires-Dist: numpy
Requires-Dist: pandas
Requires-Dist: pytest
Requires-Dist: pytest-cov
Requires-Dist: python-casacore
Requires-Dist: python-dateutil
Requires-Dist: pytz
Requires-Dist: scipy
Requires-Dist: sphinx
Requires-Dist: tables
Requires-Dist: tomli; python_version < '3.11'
Provides-Extra: docs
Requires-Dist: numpydoc; extra == 'docs'
Requires-Dist: pydata-sphinx-theme; extra == 'docs'
Requires-Dist: sphinx; extra == 'docs'
Requires-Dist: sphinx-autoapi; extra == 'docs'
